wordcel/__init__.py
wordcel/__main__.py
wordcel/cli.py
wordcel/cli_rich.py
wordcel/config.py
wordcel/dag/__init__.py
wordcel/dag/async_utils.py
wordcel/dag/backends.py
wordcel/dag/dag.py
wordcel/dag/default_functions.py
wordcel/dag/executors.py
wordcel/dag/nodes.py
wordcel/dag/utils.py
wordcel/featurize.py
wordcel/interactive.py
wordcel/llms.py
wordcel/logging_config.py
wordcel/rag/__init__.py
wordcel/rag/contextual_retrieval.py
wordcel/rag/utils.py
wordcel-0.4.4.dist-info/LICENSE
wordcel-0.4.4.dist-info/METADATA
wordcel-0.4.4.dist-info/WHEEL
wordcel-0.4.4.dist-info/entry_points.txt
wordcel-0.4.4.dist-info/RECORD
