Metadata-Version: 2.3
Name: wordcel
Version: 0.4.4
Summary: Swiss army-knife for composing LLM outputs
Author: Andrew Han
Author-email: handrew11@gmail.com
Requires-Python: >=3.9,<4.0
Classifier: Programming Language :: Python :: 3
Classifier: Programming Language :: Python :: 3.9
Classifier: Programming Language :: Python :: 3.10
Classifier: Programming Language :: Python :: 3.11
Classifier: Programming Language :: Python :: 3.12
Classifier: Programming Language :: Python :: 3.13
Requires-Dist: click
Requires-Dist: graphviz
Requires-Dist: langchain (>0.3.0)
Requires-Dist: litellm
Requires-Dist: matplotlib
Requires-Dist: networkx
Requires-Dist: openai (>1.0)
Requires-Dist: pandas
Requires-Dist: rich (>=13.0.0)
Requires-Dist: scikit-learn
Requires-Dist: tenacity
